digraphx/__init__.py
digraphx/min_cycle_ratio.py
digraphx/min_parmetric_q.py
digraphx/neg_cycle.py
digraphx/neg_cycle_q.py
digraphx/parametric.py
digraphx/skeleton.py
digraphx/tiny_digraph.py
digraphx-0.2.dist-info/licenses/LICENSE.txt
digraphx-0.2.dist-info/METADATA
digraphx-0.2.dist-info/WHEEL
digraphx-0.2.dist-info/top_level.txt
digraphx-0.2.dist-info/RECORD
