Metadata-Version: 2.4
Name: digraphx
Version: 0.2
Summary: Network Optimization Python Code
Home-page: https://github.com/luk036/digraphx
Author: Wai-Shing Luk
Author-email: luk036@gmail.com
License: MIT
Project-URL: Documentation, https://pyscaffold.org/
Platform: any
Classifier: Development Status :: 4 - Beta
Classifier: Programming Language :: Python
License-File: LICENSE.txt
Requires-Dist: importlib-metadata; python_version < "3.9"
Requires-Dist: networkx
Provides-Extra: testing
Requires-Dist: setuptools; extra == "testing"
Requires-Dist: pytest; extra == "testing"
Requires-Dist: pytest-cov; extra == "testing"
Requires-Dist: networkx; extra == "testing"
Dynamic: license-file
